principalmapper/__init__.py
principalmapper/__main__.py
principalmapper/analysis/__init__.py
principalmapper/analysis/cli.py
principalmapper/analysis/find_risks.py
principalmapper/analysis/finding.py
principalmapper/analysis/report.py
principalmapper/common/__init__.py
principalmapper/common/edges.py
principalmapper/common/graphs.py
principalmapper/common/groups.py
principalmapper/common/nodes.py
principalmapper/common/org_trees.py
principalmapper/common/policies.py
principalmapper/graphing/__init__.py
principalmapper/graphing/autoscaling_edges.py
principalmapper/graphing/cloudformation_edges.py
principalmapper/graphing/codebuild_edges.py
principalmapper/graphing/cross_account_edges.py
principalmapper/graphing/ec2_edges.py
principalmapper/graphing/edge_checker.py
principalmapper/graphing/edge_identification.py
principalmapper/graphing/gathering.py
principalmapper/graphing/graph_actions.py
principalmapper/graphing/graph_cli.py
principalmapper/graphing/iam_edges.py
principalmapper/graphing/lambda_edges.py
principalmapper/graphing/orgs_cli.py
principalmapper/graphing/sagemaker_edges.py
principalmapper/graphing/ssm_edges.py
principalmapper/graphing/sts_edges.py
principalmapper/querying/__init__.py
principalmapper/querying/argquery_cli.py
principalmapper/querying/local_policy_simulation.py
principalmapper/querying/query_actions.py
principalmapper/querying/query_cli.py
principalmapper/querying/query_interface.py
principalmapper/querying/query_orgs.py
principalmapper/querying/query_result.py
principalmapper/querying/query_utils.py
principalmapper/querying/repl.py
principalmapper/querying/repl_cli.py
principalmapper/querying/presets/__init__.py
principalmapper/querying/presets/clusters.py
principalmapper/querying/presets/connected.py
principalmapper/querying/presets/endgame.py
principalmapper/querying/presets/privesc.py
principalmapper/querying/presets/serviceaccess.py
principalmapper/querying/presets/wrongadmin.py
principalmapper/util/__init__.py
principalmapper-1.1.5.dist-info/LICENSE
principalmapper-1.1.5.dist-info/METADATA
principalmapper-1.1.5.dist-info/WHEEL
principalmapper-1.1.5.dist-info/entry_points.txt
principalmapper-1.1.5.dist-info/top_level.txt
principalmapper-1.1.5.dist-info/RECORD
